streamlit_action_progress/__init__.py
streamlit_action_progress/example.py
streamlit_action_progress/frontend/build/asset-manifest.json
streamlit_action_progress/frontend/build/bootstrap.min.css
streamlit_action_progress/frontend/build/index.html
streamlit_action_progress/frontend/build/static/js/main.8602db9c.js
streamlit_action_progress/frontend/build/static/js/main.8602db9c.js.LICENSE.txt
streamlit_action_progress/frontend/build/static/js/main.8602db9c.js.map
streamlit_action_progress-0.2.1.dist-info/licenses/LICENSE
streamlit_action_progress-0.2.1.dist-info/METADATA
streamlit_action_progress-0.2.1.dist-info/WHEEL
streamlit_action_progress-0.2.1.dist-info/top_level.txt
streamlit_action_progress-0.2.1.dist-info/RECORD
